Metadata-Version: 2.1
Name: odoo10-addon-account-invoice-transmit-method
Version: 10.0.1.0.1
Summary: Configure invoice transmit method (email, post, portal, ...)
Home-page: https://github.com/OCA/account-invoicing
Author: Akretion,Odoo Community Association (OCA)
Author-email: support@odoo-community.org
License: AGPL-3
Platform: UNKNOWN
Classifier: Programming Language :: Python
Classifier: Framework :: Odoo
Classifier: License :: OSI Approved :: GNU Affero General Public License v3
Requires-Python: ~=2.7
Requires-Dist: odoo10-addon-base-view-inheritance-extension
Requires-Dist: odoo (<10.1dev,>=10.0)
